{"cameraMode":{"drawMode":0,"name":"Shaded","section":"Shading Mode"},"sceneLighting":true,"audioPlay":false,"sceneViewState":{"showFog":true,"showMaterialUpdate":false,"showSkybox":true,"showFlares":true,"showImageEffects":true,"showParticleSystems":true},"in2DMode":false,"pivot":{"x":399.9923400878906,"y":1.9638347625732422,"z":380.16510009765627},"rotation":{"x":-0.00007958144851727411,"y":-0.9909141063690186,"z":0.13459208607673646,"w":-0.0005988098564557731},"size":10.0,"orthographic":false}